xtrmth/__init__.py
xtrmth/myfunctions.py
xtrmth/xm.py
xtrmth-1.6.1.dist-info/LICENCE
xtrmth-1.6.1.dist-info/METADATA
xtrmth-1.6.1.dist-info/WHEEL
xtrmth-1.6.1.dist-info/top_level.txt
xtrmth-1.6.1.dist-info/RECORD
